sardana_limaccd/__init__.py
sardana_limaccd/client.py
sardana_limaccd/ctrl/LimaCCDCtrl.py
sardana_limaccd/ctrl/LimaRoICounterCtrl.py
sardana_limaccd/ctrl/LimaXspress3ScalarsCtrl.py
sardana_limaccd/ctrl/__init__.py
sardana_limaccd/macro/__init__.py
sardana_limaccd/macro/limaccd.py
sardana_limaccd-0.12.0.dist-info/licenses/LICENSE
sardana_limaccd-0.12.0.dist-info/METADATA
sardana_limaccd-0.12.0.dist-info/WHEEL
sardana_limaccd-0.12.0.dist-info/top_level.txt
sardana_limaccd-0.12.0.dist-info/RECORD
