Metadata-Version: 2.4
Name: sardana_limaccd
Version: 0.12.0
Summary: LimaCCD Sardana plugin (controllers, macros, tools)
Home-page: https://github.com/ALBA-Synchrotron/sardana-limaccd
Author: ALBA controls team
Author-email: controls@cells.es
License: GPLv3
Requires-Python: >=3.5
License-File: LICENSE
Requires-Dist: sardana
Dynamic: author
Dynamic: author-email
Dynamic: home-page
Dynamic: license
Dynamic: license-file
Dynamic: requires-dist
Dynamic: requires-python
Dynamic: summary
